tamarin_wrapper/__init__.py
tamarin_wrapper/main.py
tamarin_wrapper/runner.py
tamarin_wrapper/model/__init__.py
tamarin_wrapper/model/executable_task.py
tamarin_wrapper/model/tamarin_recipe.py
tamarin_wrapper/modules/__init__.py
tamarin_wrapper/modules/config_manager.py
tamarin_wrapper/modules/output_manager.py
tamarin_wrapper/modules/process_manager.py
tamarin_wrapper/modules/resource_manager.py
tamarin_wrapper/modules/tamarin_test_cmd.py
tamarin_wrapper/modules/task_manager.py
tamarin_wrapper/utils/__init__.py
tamarin_wrapper/utils/notifications.py
tamarin_wrapper/utils/system_resources.py
tamarin_wrapper-0.1.12.dist-info/licenses/LICENCE
tamarin_wrapper-0.1.12.dist-info/METADATA
tamarin_wrapper-0.1.12.dist-info/WHEEL
tamarin_wrapper-0.1.12.dist-info/entry_points.txt
tamarin_wrapper-0.1.12.dist-info/top_level.txt
tamarin_wrapper-0.1.12.dist-info/RECORD
