Metadata-Version: 2.4
Name: tamarin-wrapper
Version: 0.1.12
Summary: Python wrapper for Tamarin Prover with JSON configuration
Author-email: Luca Mandrelli <luca.mandrelli@icloud.com>
License: GPL-3.0-or-later
Project-URL: Homepage, https://github.com/yourusername/tamarin-wrapper
Project-URL: Repository, https://github.com/yourusername/tamarin-wrapper
Project-URL: Documentation, https://github.com/yourusername/tamarin-wrapper#readme
Project-URL: Bug Tracker, https://github.com/yourusername/tamarin-wrapper/issues
Keywords: tamarin,prover,security,protocol,verification
Classifier: Development Status :: 4 - Beta
Classifier: Intended Audience :: Developers
Classifier: Intended Audience :: Science/Research
Classifier: License :: OSI Approved :: GNU General Public License v3 or later (GPLv3+)
Classifier: Operating System :: OS Independent
Classifier: Programming Language :: Python :: 3
Classifier: Programming Language :: Python :: 3.9
Classifier: Programming Language :: Python :: 3.10
Classifier: Programming Language :: Python :: 3.11
Classifier: Programming Language :: Python :: 3.12
Classifier: Topic :: Scientific/Engineering
Classifier: Topic :: Security
Requires-Python: >=3.9
License-File: LICENCE
Requires-Dist: typer>=0.15.0
Requires-Dist: pydantic>=2.11.0
Requires-Dist: psutil>=7.0.0
Provides-Extra: dev
Requires-Dist: black>=25.1.0; extra == "dev"
Requires-Dist: isort>=6.0.1; extra == "dev"
Requires-Dist: autoflake>=2.3.1; extra == "dev"
Requires-Dist: pre-commit>=4.2.0; extra == "dev"
Requires-Dist: pytest>=8.3.5; extra == "dev"
Requires-Dist: build>=1.0.0; extra == "dev"
Requires-Dist: twine>=4.0.0; extra == "dev"
Requires-Dist: setuptools>=61.0; extra == "dev"
Requires-Dist: wheel>=0.40.0; extra == "dev"
Dynamic: license-file
